ape_arbitrum/__init__.py
ape_arbitrum/ecosystem.py
ape_arbitrum/py.typed
ape_arbitrum/version.py
ape_arbitrum-0.8.5.dist-info/licenses/LICENSE
ape_arbitrum-0.8.5.dist-info/METADATA
ape_arbitrum-0.8.5.dist-info/WHEEL
ape_arbitrum-0.8.5.dist-info/top_level.txt
ape_arbitrum-0.8.5.dist-info/RECORD
